__init__.py
luca_api/__init__.py
luca_api/setup.py
luca_api/Canlib_src/Can_control.py
luca_api/Canlib_src/__init__.py
luca_api/Canlib_src/canalystii.py
luca_api/Movement/__init__.py
luca_api/Movement/forward_reverse.py
luca_api/Velocity/__init__.py
luca_api/Velocity/vec_and_pulse.py
luca_api/utils/__init__.py
luca_api/utils/math_processing.py
luca_api-0.0.8.dist-info/LICENSE
luca_api-0.0.8.dist-info/METADATA
luca_api-0.0.8.dist-info/WHEEL
luca_api-0.0.8.dist-info/top_level.txt
luca_api-0.0.8.dist-info/RECORD
