Metadata-Version: 2.1
Name: luca_api
Version: 0.0.8
Summary: Robot Luca API package
Author-email: HorusAI <quyennt@horusvn.com>
Classifier: Programming Language :: Python :: 3
Classifier: License :: OSI Approved :: MIT License
Classifier: Operating System :: OS Independent
License-File: LICENSE
